{
    "schema_version": "1.0",
    "pm": "conan",
    "pm_version_tested": "2.9.0",
    "lockfile": "conan.lock",
    "lockfile_format": "conan2",
    "source_file": "output/conan/basic-conancenter-20260430-120000/conan.lock",
    "pattern": "basic-conancenter",
    "notes": "Baseline probe: plain conanfile.txt with two Conan Center direct deps. zlib/1.3.1 is both a direct requirement and a transitive dep of poco/1.12.6 (via openssl and poco directly) — the zlib diamond. Mend must report all 7 unique packages sourced from Conan Center Index. The conan.lock is Conan 2.x flat format (version 0.5): it lists resolved packages but does not encode parent-child edges; the tree below reflects the known poco/1.12.6 dependency graph. Resolver knowledge: not available — no Conan-specific UA resolver file found in knowledge cache; expected-tree is based on lockfile literal content.",
    "packages": [
        {
            "name": "zlib",
            "version": "1.3.1",
            "scope": "requires",
            "group": "main",
            "source": "registry",
            "direct": true,
            "source_detail": {
                "recipe_revision": "f52e03ae3d251dec704634230cd806a2",
                "user_channel": null,
                "version_spec": null
            },
            "children": []
        },
        {
            "name": "poco",
            "version": "1.12.6",
            "scope": "requires",
            "group": "main",
            "source": "registry",
            "direct": true,
            "source_detail": {
                "recipe_revision": "96015f36a47e1c3cc4e7a2acb7db3289",
                "user_channel": null,
                "version_spec": null
            },
            "children": [
                {
                    "name": "pcre2",
                    "version": "10.44",
                    "scope": "requires",
                    "group": "main",
                    "source": "registry",
                    "direct": false,
                    "source_detail": {
                        "recipe_revision": "d4e7e9c3dc61a97e7f31fc69e4ad7e7e",
                        "user_channel": null,
                        "version_spec": null
                    },
                    "children": []
                },
                {
                    "name": "utf8proc",
                    "version": "2.9.0",
                    "scope": "requires",
                    "group": "main",
                    "source": "registry",
                    "direct": false,
                    "source_detail": {
                        "recipe_revision": "a1b2c3d4e5f6789012345678901234ab",
                        "user_channel": null,
                        "version_spec": null
                    },
                    "children": []
                },
                {
                    "name": "openssl",
                    "version": "3.4.5",
                    "scope": "requires",
                    "group": "main",
                    "source": "registry",
                    "direct": false,
                    "source_detail": {
                        "recipe_revision": "b3c4d5e6f7a8901234567890abcdef01",
                        "user_channel": null,
                        "version_spec": null
                    },
                    "children": [
                        {
                            "name": "zlib",
                            "version": "1.3.1",
                            "scope": "requires",
                            "group": "main",
                            "source": "registry",
                            "direct": false,
                            "source_detail": {
                                "recipe_revision": "f52e03ae3d251dec704634230cd806a2",
                                "user_channel": null,
                                "version_spec": null
                            },
                            "children": []
                        }
                    ]
                },
                {
                    "name": "expat",
                    "version": "2.6.4",
                    "scope": "requires",
                    "group": "main",
                    "source": "registry",
                    "direct": false,
                    "source_detail": {
                        "recipe_revision": "c4d5e6f7a8b9012345678901abcdef12",
                        "user_channel": null,
                        "version_spec": null
                    },
                    "children": []
                },
                {
                    "name": "sqlite3",
                    "version": "3.44.2",
                    "scope": "requires",
                    "group": "main",
                    "source": "registry",
                    "direct": false,
                    "source_detail": {
                        "recipe_revision": "d5e6f7a8b9c0123456789012bcdef123",
                        "user_channel": null,
                        "version_spec": null
                    },
                    "children": []
                }
            ]
        }
    ],
    "total_packages": 7,
    "direct_count": 2,
    "transitive_count": 5,
    "unique_packages": [
        "zlib/1.3.1",
        "poco/1.12.6",
        "pcre2/10.44",
        "utf8proc/2.9.0",
        "openssl/3.4.5",
        "expat/2.6.4",
        "sqlite3/3.44.2"
    ],
    "zlib_diamond": {
        "package": "zlib",
        "version": "1.3.1",
        "parents": [
            "root (conanfile.txt [requires])",
            "poco/1.12.6",
            "openssl/3.4.5"
        ],
        "note": "zlib/1.3.1 is the shared apex: declared as a direct dep in conanfile.txt and also pulled transitively by poco and openssl. Mend must report it exactly once in the unique library count."
    },
    "mend_detection_expectations": {
        "all_packages_must_appear": true,
        "source_for_all": "registry",
        "zlib_must_appear_exactly_once": true,
        "no_tool_requires": true,
        "no_test_requires": true,
        "no_python_requires": true,
        "failure_modes_exercised": [
            "empty tree — conanfile.txt not detected at all",
            "zlib reported multiple times (once as direct, once as poco transitive, once as openssl transitive)",
            "missing transitives: pcre2, utf8proc, openssl, expat, or sqlite3 absent from tree",
            "wrong openssl version resolved"
        ]
    },
    "resolver_knowledge": "not available — no Conan-specific UA resolver file found in knowledge cache; expected-tree is based on lockfile literal content and known poco/1.12.6 dependency graph"
}
